setup.py
sdc/rabbit/__init__.py
sdc/rabbit/async_consumer.py
sdc/rabbit/consumer.py
sdc/rabbit/exceptions.py
sdc/rabbit/publisher.py
sdc/rabbit/test/__init__.py
sdc/rabbit/test/receipt_404.xml
sdc/rabbit/test/receipt_incorrect_ru_ce.xml
sdc/rabbit/test/test_consumer.py
sdc/rabbit/test/test_data.py
sdc/rabbit/test/test_publisher.py
sdc_rabbit_python.egg-info/PKG-INFO
sdc_rabbit_python.egg-info/SOURCES.txt
sdc_rabbit_python.egg-info/dependency_links.txt
sdc_rabbit_python.egg-info/entry_points.txt
sdc_rabbit_python.egg-info/not-zip-safe
sdc_rabbit_python.egg-info/requires.txt
sdc_rabbit_python.egg-info/top_level.txt