Metadata-Version: 1.1
Name: sdc-rabbit-python
Version: 0.1.0
Summary: A shared library for SDC services that interact with RabbitMQ using Pika
Home-page: https://github.com/ONSdigital/sdxc-rabbit-python
Author: J Gardiner
Author-email: james@jgardiner.co.uk
License: UNKNOWN
Platform: UNKNOWN
Classifier: Operating System :: OS Independent
Classifier: Programming Language :: Python :: 3.4
Classifier: Programming Language :: Python :: 3.5
Classifier: Programming Language :: Python :: 3.6
Classifier: License :: OSI Approved :: MIT License
